cbasyncio/__init__.py
cbasyncio/_types.py
cbasyncio/aio.py
cbasyncio/asyncer.py
cbasyncio/context.py
cbasyncio/errors.py
cbasyncio/fileio.py
cbasyncio/fork.py
cbasyncio/gather.py
cbasyncio/limits.py
cbasyncio/runvars.py
cbasyncio/streamz/__init__.py
cbasyncio/streamz/channel.py
cbasyncio/streamz/stream.py
cbasyncio/streamz/toolz.py
cbasyncio/timer.py
cbasyncio/to_thread.py
cbasyncio/types.py
cbasyncio/utils.py
cbasyncio-0.0.1.dist-info/WHEEL
cbasyncio-0.0.1.dist-info/METADATA
cbasyncio-0.0.1.dist-info/RECORD
